euniverse/__init__.py
euniverse/astronomical_viewer.pro
euniverse/catalog_manager.py
euniverse/catalog_plotter.py
euniverse/catalog_plotter.ui
euniverse/control_dock.py
euniverse/control_dock.ui
euniverse/euniverse.py
euniverse/generate_icons.py
euniverse/image_viewer.py
euniverse/table_dialog.py
euniverse/wcs_utils.py
euniverse-0.9.1.dist-info/licenses/LICENSE
euniverse-0.9.1.dist-info/METADATA
euniverse-0.9.1.dist-info/WHEEL
euniverse-0.9.1.dist-info/entry_points.txt
euniverse-0.9.1.dist-info/top_level.txt
euniverse-0.9.1.dist-info/RECORD
