Metadata-Version: 2.4
Name: euniverse
Version: 0.9.1
Summary: A comprehensive tool to visualize Euclid color images created with eummy, and associated catalogs
Author-email: Mischa Schirmer <your@email.com>
License: GPL-3.0-or-later
Classifier: Programming Language :: Python :: 3
Classifier: License :: OSI Approved :: GNU General Public License v3 (GPLv3)
Classifier: Topic :: Scientific/Engineering :: Astronomy
Classifier: Intended Audience :: Science/Research
Requires-Python: >=3.7
License-File: LICENSE
Requires-Dist: PyQt5
Requires-Dist: numpy
Requires-Dist: astropy>=5.2
Requires-Dist: matplotlib
Requires-Dist: opencv-python
Requires-Dist: scipy
Requires-Dist: tifffile
Requires-Dist: requests
Requires-Dist: eummy
Dynamic: license-file
